numlockw/__init__.py
numlockw/__main__.py
numlockw-0.1.6.dist-info/licenses/LICENSE
numlockw-0.1.6.dist-info/METADATA
numlockw-0.1.6.dist-info/WHEEL
numlockw-0.1.6.dist-info/entry_points.txt
numlockw-0.1.6.dist-info/top_level.txt
numlockw-0.1.6.dist-info/RECORD
