Metadata-Version: 2.4
Name: numlockw
Version: 0.1.6
Summary: Control the state of NumLock
Author-email: xz-dev <xiangzhedev@gmail.com>
License-Expression: MIT
Project-URL: Homepage, https://github.com/xz-dev/numlockw
Project-URL: Issues, https://github.com/xz-dev/numlockw/issues
Classifier: Programming Language :: Python :: 3
Classifier: Operating System :: OS Independent
Requires-Python: >=3.9
License-File: LICENSE
Requires-Dist: evdev==1.9.2
Dynamic: license-file
